{
  "Robert Silverberg": [
    {
      "magazine": "Galaxy Magazine April 1966",
      "novel": "Lazarus Come Forth"
    },
    {
      "magazine": "Galaxy Magazine April 1970",
      "novel": "The Tower of Glass"
    },
    {
      "magazine": "Galaxy Magazine April 1971",
      "novel": "A Time of Changes"
    },
    {
      "magazine": "Galaxy Magazine August 1957",
      "novel": "Blaze of Glory"
    },
    {
      "magazine": "Galaxy Magazine August 1959",
      "novel": "Mugwump Four"
    },
    {
      "magazine": "Galaxy Magazine August 1963",
      "novel": "The Pain Peddlers"
    }
  ]
}